{
  "events": [
    {
      "title": "Machine Learning Toronto (MLTO) - January 2025",
      "time": "6:00 PM",
      "location": null,
      "url": null,
      "scraped_at": "2026-01-28T01:23:34.266876"
    },
    {
      "title": "Santacollider: Toronto Tech Community HOLIDAY PARTY ⚛️🎅🎄brought to you by SUPERCOLLIDER",
      "time": "6:00 PM",
      "location": null,
      "url": null,
      "scraped_at": "2026-01-28T01:23:34.664446"
    },
    {
      "title": "Machine Learning Toronto (MLTO) - December 2025",
      "time": "6:00 PM",
      "location": null,
      "url": null,
      "scraped_at": "2026-01-28T01:23:35.239668"
    },
    {
      "title": "MLTO Executive AI Panel - Balancing AI Innovation with Safety: Perspectives from Industry & Academia",
      "time": "5:30 PM",
      "location": "Index Exchange",
      "url": null,
      "scraped_at": "2026-01-28T01:23:35.552586"
    },
    {
      "title": "Machine Learning Toronto (MLTO) - September 2025",
      "time": "6:00 PM",
      "location": null,
      "url": null,
      "scraped_at": "2026-01-28T01:23:36.097507"
    },
    {
      "title": "Machine Learning Toronto (MLTO) - August 2025",
      "time": "6:00 PM",
      "location": null,
      "url": null,
      "scraped_at": "2026-01-28T01:23:36.666090"
    },
    {
      "title": "MLTO: Machine Learning Toronto - July 2025",
      "time": "6:00 PM",
      "location": "Left Field Brewery (Liberty Village)",
      "url": null,
      "scraped_at": "2026-01-28T01:23:36.969692"
    },
    {
      "title": "SUPERCOLLIDER: TORONTO TECH WEEK AFTERPARTY",
      "time": "8:00 PM",
      "location": "GRETA Bar YYZ",
      "url": null,
      "scraped_at": "2026-01-28T01:23:37.254887"
    },
    {
      "title": "MLTO: Machine Learning Toronto - June 2025",
      "time": "6:00 PM",
      "location": "Left Field Brewery (Liberty Village)",
      "url": null,
      "scraped_at": "2026-01-28T01:23:37.564017"
    },
    {
      "title": "Scaling ML in Enterprises: An Evening with Cohere hosted by Index Exchange",
      "time": "6:00 PM",
      "location": "Scaling ML in Enterprises: An Evening with Cohere hosted by Index Exchange",
      "url": null,
      "scraped_at": "2026-01-28T01:23:37.695578"
    }
  ],
  "debug_info": {
    "scraped_at": "2026-01-28T01:23:37.764455",
    "url": "https://lu.ma/mlto?period=past",
    "events_found": 10,
    "method": "selenium_automated"
  }
}